pyzmq-26.0.0.dist-info/RECORD
pyzmq-26.0.0.dist-info/WHEEL
pyzmq-26.0.0.dist-info/entry_points.txt
pyzmq-26.0.0.dist-info/METADATA
pyzmq-26.0.0.dist-info/licenses/LICENSE.md
pyzmq-26.0.0.dist-info/licenses/licenses/LICENSE.libsodium.txt
pyzmq-26.0.0.dist-info/licenses/licenses/LICENSE.zeromq.txt
zmq/_typing.py
zmq/error.py
zmq/__init__.pyi
zmq/_future.py
zmq/__init__.pxd
zmq/asyncio.py
zmq/constants.py
zmq/__init__.py
zmq/py.typed
zmq/decorators.py
zmq/green/device.py
zmq/green/__init__.py
zmq/green/core.py
zmq/green/poll.py
zmq/green/eventloop/__init__.py
zmq/green/eventloop/ioloop.py
zmq/green/eventloop/zmqstream.py
zmq/sugar/version.py
zmq/sugar/__init__.pyi
zmq/sugar/attrsettr.py
zmq/sugar/__init__.py
zmq/sugar/stopwatch.py
zmq/sugar/context.py
zmq/sugar/frame.py
zmq/sugar/tracker.py
zmq/sugar/poll.py
zmq/sugar/socket.py
zmq/auth/thread.py
zmq/auth/certs.py
zmq/auth/asyncio.py
zmq/auth/__init__.py
zmq/auth/ioloop.py
zmq/auth/base.py
zmq/tests/test_ioloop.py
zmq/tests/test_version.py
zmq/tests/test_monitor.py
zmq/tests/test_security.py
zmq/tests/conftest.py
zmq/tests/test_decorators.py
zmq/tests/cython_ext.pyx
zmq/tests/test_etc.py
zmq/tests/test_pubsub.py
zmq/tests/test_auth.py
zmq/tests/test_includes.py
zmq/tests/test_mypy.py
zmq/tests/test_future.py
zmq/tests/test_zmqstream.py
zmq/tests/test_message.py
zmq/tests/test_cffi_backend.py
zmq/tests/test_imports.py
zmq/tests/test_socket.py
zmq/tests/test_draft.py
zmq/tests/__init__.py
zmq/tests/test_asyncio.py
zmq/tests/test_log.py
zmq/tests/test_ssh.py
zmq/tests/test_cython.py
zmq/tests/test_retry_eintr.py
zmq/tests/test_z85.py
zmq/tests/test_error.py
zmq/tests/test_reqrep.py
zmq/tests/test_ext.py
zmq/tests/test_multipart.py
zmq/tests/test_context.py
zmq/tests/test_proxy_steerable.py
zmq/tests/test_device.py
zmq/tests/test_pair.py
zmq/tests/test_constants.py
zmq/tests/test_monqueue.py
zmq/tests/test_poll.py
zmq/tests/test_win32_shim.py
zmq/utils/strtypes.py
zmq/utils/getpid_compat.h
zmq/utils/monitor.py
zmq/utils/pyversion_compat.h
zmq/utils/zmq_compat.h
zmq/utils/__init__.py
zmq/utils/win32.py
zmq/utils/interop.py
zmq/utils/jsonapi.py
zmq/utils/mutex.h
zmq/utils/buffers.pxd
zmq/utils/z85.py
zmq/utils/garbage.py
