Metadata-Version: 2.1
Name: pyzmq
Version: 26.0.0
Summary: Python bindings for 0MQ
Author: Brian E. Granger, Min Ragan-Kelley
Author-Email: PyZMQ Contributors <zeromq-dev@lists.zeromq.org>
License: BSD 3-Clause License
Classifier: Development Status :: 5 - Production/Stable
Classifier: Intended Audience :: Developers
Classifier: Intended Audience :: Science/Research
Classifier: Intended Audience :: System Administrators
Classifier: License :: OSI Approved :: BSD License
Classifier: Operating System :: MacOS :: MacOS X
Classifier: Operating System :: Microsoft :: Windows
Classifier: Operating System :: POSIX
Classifier: Topic :: System :: Networking
Classifier: Programming Language :: Python :: 3
Classifier: Programming Language :: Python :: 3 :: Only
Classifier: Programming Language :: Python :: 3.7
Classifier: Programming Language :: Python :: 3.8
Classifier: Programming Language :: Python :: 3.9
Classifier: Programming Language :: Python :: 3.10
Classifier: Programming Language :: Python :: 3.11
Classifier: Programming Language :: Python :: 3.12
Project-URL: Homepage, https://pyzmq.readthedocs.org
Project-URL: Documentation, https://pyzmq.readthedocs.org
Project-URL: Source, https://github.com/zeromq/pyzmq
Project-URL: Tracker, https://github.com/zeromq/pyzmq/issues
Requires-Python: >=3.7
Requires-Dist: cffi; implementation_name == "pypy"
